{
  "READ_THIS_FIRST": {
    "instruction_for_ai": "DO NOT calculate totals from individual activities. Use the pre-calculated values in 'summary', 'weekly_summary', and 'derived_metrics' sections below. These are already computed accurately from the API data.",
    "display_formatting": "For durations and sleep, always display the '_formatted' fields (e.g., sleep_formatted, duration_formatted, total_training_formatted) instead of converting decimal '_hours' values. The formatted fields are pre-calculated from raw seconds and avoid rounding errors.",
    "data_period": "Last 7 days (including today)",
    "extended_data_note": "ACWR and baselines calculated from 28 days of data",
    "capability_metrics_note": "The 'capability' block in derived_metrics contains durability trend (aggregate decoupling 7d/28d), efficiency factor trend (aggregate EF 7d/28d), and TID comparison (7d vs 28d distribution drift). These measure HOW the athlete expresses fitness, not just load. Use these for coaching context alongside traditional load metrics. Durability and EF trend direction matters more than absolute values.",
    "quick_stats": {
      "total_training_hours": 7.74,
      "total_training_formatted": "7h44m",
      "total_activities": 7,
      "total_tss": 470
    }
  },
  "metadata": {
    "athlete_id": "REDACTED",
    "last_updated": "2026-04-17T13:11:43.563439",
    "data_range_days": 7,
    "extended_range_days": 28,
    "version": "3.7"
  },
  "alerts": [
    {
      "metric": "acwr",
      "value": 0.77,
      "severity": "warning",
      "threshold": "0.8 / 1.3",
      "context": "ACWR 0.77 at edge of optimal range. Monitor closely. Alarm at 0.75/1.35.",
      "persistence_days": null,
      "tier": 2
    }
  ],
  "history": {
    "available": true,
    "last_generated": "2026-04-06",
    "age_days": 11,
    "total_months": 19,
    "history_confidence": "high"
  },
  "summary": {
    "period_description": "Last 7 days of training (including today)",
    "note": "Duration calculated from API moving_time field.",
    "total_duration_decimal_hours": 7.74,
    "total_activities": 7,
    "by_activity_type": {
      "MountainBikeRide": {
        "duration_decimal_hours": 3.23,
        "count": 1,
        "tss": 137,
        "distance_km": 59.2
      },
      "Run": {
        "duration_decimal_hours": 3.33,
        "count": 4,
        "tss": 246,
        "distance_km": 45.9
      },
      "Swim": {
        "duration_decimal_hours": 1.17,
        "count": 2,
        "tss": 87,
        "distance_km": 4.7
      }
    }
  },
  "current_status": {
    "fitness": {
      "ctl": 78.8,
      "atl": 68.38,
      "tsb": 10.42,
      "ramp_rate": -2.43,
      "fitness_source": "From Intervals.icu API (reflects completed workouts)"
    },
    "thresholds": {
      "eftp": 292.7,
      "w_prime": 24830,
      "w_prime_kj": 24.8,
      "p_max": 986,
      "vo2max": null,
      "sports": {
        "cycling": {
          "lthr": 165,
          "max_hr": 184,
          "threshold_pace": null,
          "pace_units": null,
          "ftp": 280,
          "ftp_indoor": null
        },
        "run": {
          "lthr": 175,
          "max_hr": 195,
          "threshold_pace": 4.4444447,
          "pace_units": "MINS_KM",
          "ftp": 450,
          "ftp_indoor": null
        },
        "swim": {
          "lthr": 150,
          "max_hr": 180,
          "threshold_pace": 1.25,
          "pace_units": "SECS_100M",
          "ftp": null,
          "ftp_indoor": null
        }
      }
    },
    "current_metrics": {
      "weight_kg": 71.0,
      "resting_hr": 45,
      "hrv": 113.0,
      "sleep_quality": 3,
      "sleep_hours": 6.82,
      "sleep_formatted": "6h49m"
    }
  },
  "derived_metrics": {
    "recovery_index": 0.96,
    "hrv_baseline_7d": 113.9,
    "rhr_baseline_7d": 43.7,
    "hrv_baseline_28d": 116.8,
    "rhr_baseline_28d": 43.3,
    "latest_hrv": 113.0,
    "latest_rhr": 45,
    "acwr": 0.77,
    "acwr_interpretation": "undertraining",
    "monotony": 1.3,
    "monotony_interpretation": "normal (primary sport 1.05, total 1.3 inflated by multi-sport)",
    "primary_sport": "run",
    "primary_sport_monotony": 1.05,
    "primary_sport_tss_7d": 246.0,
    "effective_monotony": 1.05,
    "multi_sport_detected": true,
    "strain": 611.0,
    "stress_tolerance": 4.7,
    "load_recovery_ratio": 4.9,
    "tss_7d_total": 470.0,
    "tss_28d_total": 2442.0,
    "zone_distribution_7d": {
      "z1_hours": 2.26,
      "z2_hours": 1.05,
      "z3_hours": 2.88,
      "z4_plus_hours": 1.55,
      "total_hours": 7.74
    },
    "grey_zone_percentage": 37.2,
    "grey_zone_note": "Gray Zone % (Z3/tempo) - minimize in polarized training",
    "quality_intensity_percentage": 20.1,
    "quality_intensity_note": "Quality Intensity % (Z4+/threshold+) - target ~20% in polarized training",
    "polarisation_index": 0.43,
    "polarisation_note": "Easy time (Z1+Z2) / Total - target ~80% in polarized training",
    "hard_days_this_week": 6,
    "hard_days_note": "Power ladder: z3+ >= 30min, z4+ >= 10min, z5+ >= 5min, z6+ >= 2min, z7 >= 1min. HR fallback (when no power): z4+ >= 10min, z5+ >= 5min. Per Seiler 3-zone model + Foster. HR-based days flagged with intensity_basis: hr",
    "seiler_tid_7d": {
      "z1_seconds": 11902,
      "z2_seconds": 10376,
      "z3_seconds": 5589,
      "z1_pct": 42.7,
      "z2_pct": 37.2,
      "z3_pct": 20.1,
      "polarization_index": null,
      "classification": "Pyramidal"
    },
    "seiler_tid_7d_primary": {
      "z1_seconds": 896,
      "z2_seconds": 8042,
      "z3_seconds": 3068,
      "z1_pct": 7.5,
      "z2_pct": 67.0,
      "z3_pct": 25.6,
      "polarization_index": null,
      "classification": "Threshold",
      "sport": "run"
    },
    "seiler_tid_28d": {
      "z1_seconds": 80475,
      "z2_seconds": 36602,
      "z3_seconds": 29626,
      "z1_pct": 54.9,
      "z2_pct": 24.9,
      "z3_pct": 20.2,
      "polarization_index": null,
      "classification": "Pyramidal"
    },
    "seiler_tid_28d_primary": {
      "z1_seconds": 7740,
      "z2_seconds": 19659,
      "z3_seconds": 9515,
      "z1_pct": 21.0,
      "z2_pct": 53.3,
      "z3_pct": 25.8,
      "polarization_index": null,
      "classification": "Threshold",
      "sport": "run"
    },
    "capability": {
      "durability": {
        "mean_decoupling_7d": null,
        "mean_decoupling_28d": null,
        "high_drift_count_7d": 0,
        "high_drift_count_28d": 0,
        "qualifying_sessions_7d": 0,
        "qualifying_sessions_28d": 0,
        "trend": null,
        "note": "Steady-state power sessions only (VI <= 1.05, VI > 0, >= 90min, power data). Negative decoupling = strong durability. Trend compares 7d vs 28d mean (+/-1% = stable)."
      },
      "efficiency_factor": {
        "mean_ef_7d": null,
        "mean_ef_28d": null,
        "qualifying_sessions_7d": 0,
        "qualifying_sessions_28d": 0,
        "trend": null,
        "note": "Steady-state cycling sessions only (VI <= 1.05, VI > 0, >= 20min, power+HR data). Rising EF = improving aerobic efficiency. Compare like-for-like sessions only \u2014 EF varies with intensity. Trend compares 7d vs 28d mean (+/-0.03 = stable)."
      },
      "tid_comparison": {
        "classification_7d": "Pyramidal",
        "classification_28d": "Pyramidal",
        "pi_7d": null,
        "pi_28d": null,
        "pi_delta": null,
        "drift": "consistent",
        "note": "Compares 7d vs 28d Seiler TID to detect distribution shifts. pi_delta positive = more polarized acutely."
      }
    },
    "consistency_index": null,
    "consistency_details": {
      "planned_days": 0,
      "completed_days": 1,
      "matched_days": 0,
      "note": "No planned workouts in period"
    },
    "phase_detection": {
      "phase": "Build",
      "confidence": "medium",
      "reason_codes": [
        "NO_PLANNED_WORKOUTS"
      ],
      "basis": {
        "stream_1": {
          "ctl_slope": 1.97,
          "acwr_trend": "rising",
          "hard_day_pattern": 4.8,
          "weeks_available": 4
        },
        "stream_2": {
          "planned_tss_delta": null,
          "hard_sessions_planned": 0,
          "race_proximity": null,
          "next_week_load": null,
          "plan_coverage_current_week": 0.0,
          "plan_coverage_next_week": 0.0
        },
        "data_quality": "good",
        "stream_agreement": null
      },
      "previous_phase": "Build",
      "phase_duration_weeks": 4,
      "dossier_declared": null,
      "dossier_agreement": null
    },
    "phase_detected": "Build",
    "phase_triggers": [
      "NO_PLANNED_WORKOUTS"
    ],
    "seasonal_context": "Late Base / Build",
    "benchmark_indoor": {
      "current_ftp": null,
      "ftp_8_weeks_ago": null,
      "benchmark_index": null,
      "benchmark_percentage": null,
      "seasonal_expected": null
    },
    "benchmark_outdoor": {
      "current_ftp": 280,
      "ftp_8_weeks_ago": null,
      "benchmark_index": null,
      "benchmark_percentage": null,
      "seasonal_expected": null
    },
    "eftp": 292.7,
    "w_prime": 24830,
    "w_prime_kj": 24.8,
    "p_max": 986,
    "power_model_source": "wellness.sportInfo",
    "vo2max": null,
    "calculation_timestamp": "2026-04-17T13:11:43.562667",
    "data_quality": {
      "hrv_data_points": 7,
      "rhr_data_points": 7,
      "activities_7d": 7,
      "activities_28d": 35,
      "planned_workouts_7d": 0,
      "ftp_history_days": {
        "indoor": 0,
        "outdoor": 0
      }
    }
  },
  "recent_activities": [
    {
      "id": "i140423998",
      "date": "2026-04-16T18:55:58",
      "type": "Run",
      "name": "Training Session",
      "duration_hours": 0.71,
      "distance_km": 10.23,
      "tss": 56,
      "intensity_factor": 90.44444,
      "avg_power": 395,
      "normalized_power": 407,
      "avg_hr": 157,
      "max_hr": 186,
      "avg_cadence": 88.52822,
      "avg_speed": 14.3,
      "max_speed": 19.5,
      "avg_pace": null,
      "avg_temp": 24.354513,
      "weather": null,
      "humidity": null,
      "wind_speed": null,
      "work_kj": 1023.7,
      "calories": 701,
      "carbs_used": null,
      "carbs_ingested": null,
      "variability_index": 1.0303798,
      "decoupling": 3.9558864,
      "efficiency_factor": 2.5923567,
      "elevation_m": 46.20996,
      "feel": 4,
      "rpe": 7,
      "zone_distribution": {
        "hr_zones": {
          "z1_time": 271,
          "z2_time": 888,
          "z3_time": 551,
          "z4_time": 592,
          "z5_time": 270
        },
        "power_zones": {
          "z1_time": 44,
          "z2_time": 190,
          "z3_time": 1371,
          "z4_time": 762,
          "z5_time": 188,
          "z6_time": 17,
          "z7_time": 0
        }
      }
    },
    {
      "id": "i140151394",
      "date": "2026-04-15T19:08:14",
      "type": "Run",
      "name": "Training Session",
      "duration_hours": 1.02,
      "distance_km": 13.44,
      "tss": 70,
      "intensity_factor": 83.55556,
      "avg_power": 375,
      "normalized_power": 376,
      "avg_hr": 141,
      "max_hr": 151,
      "avg_cadence": 86.71429,
      "avg_speed": 13.2,
      "max_speed": 15.1,
      "avg_pace": null,
      "avg_temp": 21.58727,
      "weather": null,
      "humidity": null,
      "wind_speed": null,
      "work_kj": 1371.2,
      "calories": 894,
      "carbs_used": null,
      "carbs_ingested": null,
      "variability_index": 1.0026667,
      "decoupling": 0.15584423,
      "efficiency_factor": 2.6666667,
      "elevation_m": 86.95008,
      "feel": 2,
      "rpe": 3,
      "zone_distribution": {
        "hr_zones": {
          "z1_time": 1097,
          "z2_time": 2564,
          "z3_time": 0,
          "z4_time": 0,
          "z5_time": 0
        },
        "power_zones": {
          "z1_time": 23,
          "z2_time": 143,
          "z3_time": 3284,
          "z4_time": 198,
          "z5_time": 13,
          "z6_time": 0,
          "z7_time": 0
        }
      }
    },
    {
      "id": "i139821801",
      "date": "2026-04-14T18:10:32",
      "type": "Swim",
      "name": "Piscina",
      "duration_hours": 0.77,
      "distance_km": 3.1,
      "tss": 52,
      "intensity_factor": 72.85346,
      "avg_power": null,
      "normalized_power": null,
      "avg_hr": 127,
      "max_hr": 156,
      "avg_cadence": 25.519619,
      "avg_speed": 4.1,
      "max_speed": 6.3,
      "avg_pace": null,
      "avg_temp": null,
      "weather": null,
      "humidity": null,
      "wind_speed": null,
      "work_kj": null,
      "calories": 643,
      "carbs_used": null,
      "carbs_ingested": null,
      "variability_index": null,
      "decoupling": null,
      "efficiency_factor": null,
      "elevation_m": null,
      "feel": 3,
      "rpe": 5,
      "zone_distribution": {
        "hr_zones": {
          "z1_time": 886,
          "z2_time": 306,
          "z3_time": 541,
          "z4_time": 915,
          "z5_time": 133
        }
      }
    },
    {
      "id": "i139528786",
      "date": "2026-04-13T18:48:32",
      "type": "Run",
      "name": "Training Session",
      "duration_hours": 0.81,
      "distance_km": 10.47,
      "tss": 53,
      "intensity_factor": 81.77778,
      "avg_power": 365,
      "normalized_power": 368,
      "avg_hr": 139,
      "max_hr": 152,
      "avg_cadence": 86.269905,
      "avg_speed": 12.9,
      "max_speed": 14.7,
      "avg_pace": null,
      "avg_temp": 20.497255,
      "weather": null,
      "humidity": null,
      "wind_speed": null,
      "work_kj": 1067.5,
      "calories": 691,
      "carbs_used": null,
      "carbs_ingested": null,
      "variability_index": 1.0082191,
      "decoupling": -0.49204418,
      "efficiency_factor": 2.647482,
      "elevation_m": 76.85887,
      "feel": 4,
      "rpe": 2,
      "zone_distribution": {
        "hr_zones": {
          "z1_time": 1359,
          "z2_time": 1549,
          "z3_time": 0,
          "z4_time": 0,
          "z5_time": 0
        },
        "power_zones": {
          "z1_time": 39,
          "z2_time": 383,
          "z3_time": 2343,
          "z4_time": 138,
          "z5_time": 5,
          "z6_time": 0,
          "z7_time": 0
        }
      }
    },
    {
      "id": "i139113813",
      "date": "2026-04-12T11:56:59",
      "type": "Run",
      "name": "Training Session",
      "duration_hours": 0.8,
      "distance_km": 11.71,
      "tss": 67,
      "intensity_factor": 93.77778,
      "avg_power": 417,
      "normalized_power": 422,
      "avg_hr": 161,
      "max_hr": 177,
      "avg_cadence": 87.47365,
      "avg_speed": 14.7,
      "max_speed": 15.9,
      "avg_pace": null,
      "avg_temp": 21.999651,
      "weather": null,
      "humidity": null,
      "wind_speed": null,
      "work_kj": 1195.3,
      "calories": 800,
      "carbs_used": null,
      "carbs_ingested": null,
      "variability_index": 1.0119904,
      "decoupling": -1.8662425,
      "efficiency_factor": 2.621118,
      "elevation_m": 46.73933,
      "feel": 3,
      "rpe": 6,
      "zone_distribution": {
        "hr_zones": {
          "z1_time": 202,
          "z2_time": 413,
          "z3_time": 909,
          "z4_time": 1341,
          "z5_time": 0
        },
        "power_zones": {
          "z1_time": 7,
          "z2_time": 67,
          "z3_time": 1044,
          "z4_time": 1612,
          "z5_time": 135,
          "z6_time": 0,
          "z7_time": 0
        }
      }
    },
    {
      "id": "i138960588",
      "date": "2026-04-11T17:55:54",
      "type": "Swim",
      "name": "Piscina",
      "duration_hours": 0.4,
      "distance_km": 1.6,
      "tss": 35,
      "intensity_factor": 90.5122,
      "avg_power": null,
      "normalized_power": null,
      "avg_hr": 142,
      "max_hr": 169,
      "avg_cadence": 25.115545,
      "avg_speed": 4.0,
      "max_speed": 4.9,
      "avg_pace": null,
      "avg_temp": null,
      "weather": null,
      "humidity": null,
      "wind_speed": null,
      "work_kj": null,
      "calories": 361,
      "carbs_used": null,
      "carbs_ingested": null,
      "variability_index": null,
      "decoupling": null,
      "efficiency_factor": null,
      "elevation_m": null,
      "feel": 3,
      "rpe": 3,
      "zone_distribution": {
        "hr_zones": {
          "z1_time": 93,
          "z2_time": 319,
          "z3_time": 169,
          "z4_time": 364,
          "z5_time": 483
        }
      }
    },
    {
      "id": "i138892473",
      "date": "2026-04-11T10:20:39",
      "type": "MountainBikeRide",
      "name": "Training Session",
      "duration_hours": 3.23,
      "distance_km": 59.19,
      "tss": 137,
      "intensity_factor": 64.48112,
      "avg_power": null,
      "normalized_power": null,
      "avg_hr": 125,
      "max_hr": 168,
      "avg_cadence": null,
      "avg_speed": 18.1,
      "max_speed": 50.2,
      "avg_pace": null,
      "avg_temp": 22.58834,
      "weather": null,
      "humidity": null,
      "wind_speed": null,
      "work_kj": null,
      "calories": 1796,
      "carbs_used": null,
      "carbs_ingested": null,
      "variability_index": null,
      "decoupling": null,
      "efficiency_factor": null,
      "elevation_m": 1367.0,
      "feel": null,
      "rpe": null,
      "zone_distribution": {
        "hr_zones": {
          "z1_time": 7027,
          "z2_time": 2375,
          "z3_time": 1624,
          "z4_time": 620,
          "z5_time": 6
        }
      }
    }
  ],
  "wellness_data": [
    {
      "date": "2026-04-11",
      "weight_kg": null,
      "resting_hr": 47,
      "hrv_rmssd": 93.0,
      "hrv_sdnn": null,
      "sleep_hours": 8.27,
      "sleep_formatted": "8h16m",
      "sleep_quality": 3,
      "sleep_score": 76.0,
      "mental_energy": null,
      "fatigue": null,
      "soreness": null,
      "avg_sleeping_hr": null,
      "vo2max": null
    },
    {
      "date": "2026-04-12",
      "weight_kg": null,
      "resting_hr": 45,
      "hrv_rmssd": 96.0,
      "hrv_sdnn": null,
      "sleep_hours": 7.54,
      "sleep_formatted": "7h32m",
      "sleep_quality": 3,
      "sleep_score": 69.0,
      "mental_energy": null,
      "fatigue": null,
      "soreness": null,
      "avg_sleeping_hr": null,
      "vo2max": 65.0
    },
    {
      "date": "2026-04-13",
      "weight_kg": null,
      "resting_hr": 43,
      "hrv_rmssd": 105.0,
      "hrv_sdnn": null,
      "sleep_hours": 6.5,
      "sleep_formatted": "6h30m",
      "sleep_quality": 3,
      "sleep_score": 77.0,
      "mental_energy": null,
      "fatigue": null,
      "soreness": null,
      "avg_sleeping_hr": null,
      "vo2max": 65.0
    },
    {
      "date": "2026-04-14",
      "weight_kg": null,
      "resting_hr": 44,
      "hrv_rmssd": 129.0,
      "hrv_sdnn": null,
      "sleep_hours": 7.64,
      "sleep_formatted": "7h38m",
      "sleep_quality": 1,
      "sleep_score": 93.0,
      "mental_energy": null,
      "fatigue": null,
      "soreness": null,
      "avg_sleeping_hr": null,
      "vo2max": null
    },
    {
      "date": "2026-04-15",
      "weight_kg": null,
      "resting_hr": 41,
      "hrv_rmssd": 127.0,
      "hrv_sdnn": null,
      "sleep_hours": 7.25,
      "sleep_formatted": "7h14m",
      "sleep_quality": 2,
      "sleep_score": 84.0,
      "mental_energy": null,
      "fatigue": null,
      "soreness": null,
      "avg_sleeping_hr": null,
      "vo2max": 66.0
    },
    {
      "date": "2026-04-16",
      "weight_kg": null,
      "resting_hr": 41,
      "hrv_rmssd": 134.0,
      "hrv_sdnn": null,
      "sleep_hours": 6.47,
      "sleep_formatted": "6h28m",
      "sleep_quality": 2,
      "sleep_score": 80.0,
      "mental_energy": null,
      "fatigue": null,
      "soreness": null,
      "avg_sleeping_hr": null,
      "vo2max": 65.0
    },
    {
      "date": "2026-04-17",
      "weight_kg": null,
      "resting_hr": 45,
      "hrv_rmssd": 113.0,
      "hrv_sdnn": null,
      "sleep_hours": 6.82,
      "sleep_formatted": "6h49m",
      "sleep_quality": 3,
      "sleep_score": 65.0,
      "mental_energy": null,
      "fatigue": null,
      "soreness": null,
      "avg_sleeping_hr": null,
      "vo2max": null
    }
  ],
  "planned_workouts": [],
  "workout_summary_stats": {
    "attempted": 0,
    "success": 0,
    "patternA": 0,
    "patternB": 0,
    "bail_no_workout_doc": 0,
    "bail_no_match": 0
  },
  "weekly_summary": {
    "total_training_hours": 7.74,
    "total_training_formatted": "7h44m",
    "total_tss": 470,
    "activities_count": 7,
    "avg_hrv": 113.9,
    "avg_resting_hr": 43.7
  },
  "race_calendar": {
    "next_race": null,
    "all_races": [],
    "taper_alert": {
      "active": false
    },
    "race_week": {
      "active": false
    }
  }
}